myhn.py
myhn-0.0.1.dev1.dist-info/METADATA
myhn-0.0.1.dev1.dist-info/WHEEL
myhn-0.0.1.dev1.dist-info/top_level.txt
myhn-0.0.1.dev1.dist-info/RECORD
